rust_tokenizer_sober-0.1.0.dist-info/METADATA
rust_tokenizer_sober-0.1.0.dist-info/WHEEL
rust_tokenizer_sober/__init__.py
rust_tokenizer_sober/rust_tokenizer_sober.cp311-win_amd64.pyd
rust_tokenizer_sober-0.1.0.dist-info/RECORD
