Metadata-Version: 2.4
Name: rust-tokenizer-sober
Version: 0.1.0
Summary: Fast Unicode-aware tokenizer implemented in Rust (PyO3 + maturin).
Author-email: Your Name <you@example.com>
License: MIT
Requires-Python: >=3.8
